emailtools/__init__.py
emailtools/models.py
emailtools/tests.py
emailtools/cbe/__init__.py
emailtools/cbe/base.py
emailtools/cbe/mixins.py
django_emailtools_reloaded-0.2.4.dist-info/LICENSE
django_emailtools_reloaded-0.2.4.dist-info/METADATA
django_emailtools_reloaded-0.2.4.dist-info/WHEEL
django_emailtools_reloaded-0.2.4.dist-info/top_level.txt
django_emailtools_reloaded-0.2.4.dist-info/RECORD
