Metadata-Version: 2.1
Name: django-emailtools-reloaded
Version: 0.2.4
Summary: App for Django featuring class based email sending.
Home-page: https://github.com/barseghyanartur/django-emailtools-reloaded
Author: Artur Barseghyan
Author-email: artur.barseghyan@gmail.com
License: UNKNOWN
Platform: UNKNOWN
Requires-Dist: markdown
